[
  {
    "id": "01_intro",
    "text": "Demostracion de la API de Xiaomi MIMO. Sintesis de voz y reconocimiento de audio.",
    "start": 0.0,
    "duration": 5.928
  },
  {
    "id": "02_tts_explain",
    "text": "Usamos el modelo de sintesis de voz para convertir texto en audio. La inteligencia artificial genera una voz natural en espanol.",
    "start": 5.0,
    "duration": 8.304
  },
  {
    "id": "03_api_process",
    "text": "La API procesa nuestra solicitud. El modelo mimo v2.5 genera audio desde el texto en segundos.",
    "start": 10.8324556350708,
    "duration": 7.752
  },
  {
    "id": "04_pre_play",
    "text": "Escuchen el audio generado por inteligencia artificial.",
    "start": 18.258517742156982,
    "duration": 3.792
  },
  {
    "id": "05_post_play",
    "text": "Excelente. Ahora usamos reconocimiento de voz para transcribir el audio.",
    "start": 32.87916588783264,
    "duration": 5.64
  },
  {
    "id": "06_asr_process",
    "text": "La API esta procesando el audio. Reconociendo las palabras con inteligencia artificial.",
    "start": 37.53854465484619,
    "duration": 6.288
  },
  {
    "id": "07_asr_result",
    "text": "La API reconoce las palabras y devuelve la transcripcion.",
    "start": 42.23847818374634,
    "duration": 4.008
  },
  {
    "id": "08_outro",
    "text": "Dos APIs que juntas crean un sistema de voz completo. Gracias por ver.",
    "start": 45.24329400062561,
    "duration": 5.448
  },
  {
    "id": "tts_audio",
    "text": "[TTS Audio Playing]",
    "start": 20.32080626487732,
    "duration": 12.16
  }
]